ray_cli/__init__.py
ray_cli/__main__.py
ray_cli/__version__.py
ray_cli/app.py
ray_cli/cli.py
ray_cli/core/__init__.py
ray_cli/core/sender.py
ray_cli/core/sender_pool.py
ray_cli/core/socket.py
ray_cli/core/types.py
ray_cli/modes/__init__.py
ray_cli/modes/factory.py
ray_cli/modes/generators.py
ray_cli/modes/mode.py
ray_cli/modes/types.py
ray_cli/protocols/__init__.py
ray_cli/protocols/artnet/__init__.py
ray_cli/protocols/artnet/encoder.py
ray_cli/protocols/artnet/factory.py
ray_cli/protocols/artnet/packets.py
ray_cli/protocols/artnet/sockets.py
ray_cli/protocols/sacn/__init__.py
ray_cli/protocols/sacn/encoder.py
ray_cli/protocols/sacn/factory.py
ray_cli/protocols/sacn/packets.py
ray_cli/protocols/sacn/sockets.py
ray_cli/utils/__init__.py
ray_cli/utils/cli.py
ray_cli/utils/feedback.py
ray_cli/utils/formatters.py
ray_cli/utils/progress_bar.py
ray_cli/utils/reports.py
ray_cli/utils/table_logger.py
ray_cli-1.0.3.dist-info/METADATA
ray_cli-1.0.3.dist-info/WHEEL
ray_cli-1.0.3.dist-info/entry_points.txt
ray_cli-1.0.3.dist-info/licenses/LICENSE
ray_cli-1.0.3.dist-info/RECORD
