Metadata-Version: 2.4
Name: ray-cli
Version: 1.0.3
Summary: Command-line utility for generating and broadcasting DMX over sACN and Art-Net
Project-URL: Repository, https://github.com/nobbmaestro/ray-cli
Author-email: Norbert Batiuk <norbert@batiuk.se>
License-Expression: MIT
License-File: LICENSE
Keywords: cli,dmx,python,sacn,utility
Classifier: Intended Audience :: Developers
Classifier: License :: OSI Approved :: MIT License
Classifier: Operating System :: OS Independent
Classifier: Programming Language :: Python :: 3
Requires-Python: <4.0,>=3.8
